p5control/__init__.py
p5control/settings.py
p5control/data/__init__.py
p5control/data/hdf5.py
p5control/drivers/__init__.py
p5control/drivers/basedriver.py
p5control/drivers/blueforsapi.py
p5control/drivers/exampleinst.py
p5control/drivers/exampleinst2.py
p5control/drivers/gir2002.py
p5control/drivers/keysight34461A.py
p5control/drivers/keysightB2962A.py
p5control/drivers/znb40.py
p5control/gateway/__init__.py
p5control/gateway/basegw.py
p5control/gateway/datagw.py
p5control/gateway/instgw.py
p5control/gui/__init__.py
p5control/gui/cleanupapp.py
p5control/gui/databuffer.py
p5control/gui/guidatagw.py
p5control/gui/guisettings.py
p5control/gui/viewer.py
p5control/gui/models/__init__.py
p5control/gui/models/plotconfig.py
p5control/gui/widgets/__init__.py
p5control/gui/widgets/attributestable.py
p5control/gui/widgets/datagw_plot.py
p5control/gui/widgets/datagw_treeview.py
p5control/gui/widgets/datasetdims.py
p5control/gui/widgets/datasetproperties.py
p5control/gui/widgets/datasettable.py
p5control/gui/widgets/editvaluebox.py
p5control/gui/widgets/legend.py
p5control/gui/widgets/measurementcontrol.py
p5control/gui/widgets/monitorvaluebox.py
p5control/gui/widgets/plotform.py
p5control/gui/widgets/plottabwidget.py
p5control/gui/widgets/valueboxform.py
p5control/measure/__init__.py
p5control/measure/measurement.py
p5control/measure/status.py
p5control/scripts/measurements.py
p5control/server/__init__.py
p5control/server/baseserv.py
p5control/server/control.py
p5control/server/dataserv.py
p5control/server/inserv.py
p5control/server/mockserver.py
p5control/util/__init__.py
p5control/util/asyncutil.py
p5control/util/colors.py
p5control/util/filenames.py
p5control-0.0.2.dist-info/LICENSE
p5control-0.0.2.dist-info/METADATA
p5control-0.0.2.dist-info/WHEEL
p5control-0.0.2.dist-info/entry_points.txt
p5control-0.0.2.dist-info/top_level.txt
p5control-0.0.2.dist-info/RECORD
